hackaru_timeular/__init__.py
hackaru_timeular/hackaru_timeular.py
hackaru_timeular-0.2.0.dist-info/LICENSE
hackaru_timeular-0.2.0.dist-info/METADATA
hackaru_timeular-0.2.0.dist-info/WHEEL
hackaru_timeular-0.2.0.dist-info/entry_points.txt
hackaru_timeular-0.2.0.dist-info/top_level.txt
hackaru_timeular-0.2.0.dist-info/RECORD
