Metadata-Version: 2.1
Name: hackaru-timeular
Version: 0.2.0
Summary: Track your time with the Timeular cube and Hackaru
Home-page: https://github.com/pSub/hackaru-timeular
Author: Pascal Wittmann
Author-email: github@pascal-wittmann.de
License: MIT
License-File: LICENSE
Requires-Dist: bleak
Requires-Dist: recordclass
Requires-Dist: appdirs
Requires-Dist: requests
Requires-Dist: PyYAML
Requires-Dist: tenacity
